tests/__init__.py
tests/test_contraction.py
tests/test_convert.py
tests/test_evaluate.py
tests/test_postprocessor.py
tests/test_repetition.py
tests/test_sva.py
tests/test_type_error.py
tests/test_vnerrant.py
vnerrant/__init__.py
vnerrant/annotator.py
vnerrant/config.py
vnerrant/constants.py
vnerrant/run_cli.py
vnerrant/cli/__init__.py
vnerrant/cli/convert.py
vnerrant/cli/evaluate.py
vnerrant/components/__init__.py
vnerrant/components/alignment.py
vnerrant/components/classifier.py
vnerrant/components/converter.py
vnerrant/components/evaluater.py
vnerrant/components/explainer.py
vnerrant/components/merger.py
vnerrant/components/postprocessor.py
vnerrant/components/tokenizer.py
vnerrant/components/en/__init__.py
vnerrant/components/en/classifier.py
vnerrant/components/en/constants.py
vnerrant/components/en/explainer.py
vnerrant/components/en/lancaster.py
vnerrant/components/en/merger.py
vnerrant/components/en/postprocessor.py
vnerrant/components/en/utils.py
vnerrant/components/en/resources/README.md
vnerrant/components/en/resources/en-ptb_map
vnerrant/components/en/resources/en_GB-large.txt
vnerrant/components/en/resources/filler_words.txt
vnerrant/components/en/resources/replacing.dat
vnerrant/components/en/resources/wrong_nouns.txt
vnerrant/config/errant_verbose.json
vnerrant/config/mapping_type_error.yaml
vnerrant/metrics/__init__.py
vnerrant/metrics/criteria.py
vnerrant/metrics/stats.py
vnerrant/model/__init__.py
vnerrant/model/edit.py
vnerrant/utils/__init__.py
vnerrant/utils/edit_utils.py
vnerrant/utils/helper.py
vnerrant/utils/io_utils.py
vnerrant/utils/pretty_results.py
vnerrant/utils/replacing.py
vnerrant/utils/string_utils.py
vnerrant/utils/utils.py
vnerrant/utils/wordlist.py
vnerrant-3.0.0.dist-info/METADATA
vnerrant-3.0.0.dist-info/WHEEL
vnerrant-3.0.0.dist-info/entry_points.txt
vnerrant-3.0.0.dist-info/top_level.txt
vnerrant-3.0.0.dist-info/RECORD
