Metadata-Version: 2.4
Name: vnerrant
Version: 3.0.0
Summary: The ERRor ANnotation Toolkit (ERRANT).         Automatically extract and classify edits in parallel sentences.
License: MIT
Keywords: automatic annotation,grammatical errors,natural language processing
Classifier: Development Status :: 5 - Production/Stable
Classifier: Intended Audience :: Education
Classifier: Intended Audience :: Science/Research
Classifier: License :: OSI Approved :: MIT License
Classifier: Natural Language :: English
Classifier: Operating System :: OS Independent
Classifier: Programming Language :: Python :: 3.9
Classifier: Topic :: Education
Classifier: Topic :: Scientific/Engineering :: Artificial Intelligence
Classifier: Topic :: Scientific/Engineering :: Information Analysis
Classifier: Topic :: Text Processing :: Linguistic
Requires-Python: >= 3.9
Requires-Dist: spacy>=3
Requires-Dist: rapidfuzz>=2.0.0
Dynamic: classifier
Dynamic: description
Dynamic: description-content-type
Dynamic: keywords
Dynamic: license
Dynamic: requires-dist
Dynamic: requires-python
Dynamic: summary
